solid_toolbox/__init__.py
solid_toolbox/__main__.py
solid_toolbox/commands.py
solid_toolbox/curves.py
solid_toolbox/extrusion.py
solid_toolbox/poly.py
solid_toolbox/transforms.py
solid_toolbox/units.py
solid_toolbox-0.0.6.dist-info/LICENSE.md
solid_toolbox-0.0.6.dist-info/WHEEL
solid_toolbox-0.0.6.dist-info/METADATA
solid_toolbox-0.0.6.dist-info/RECORD
